video_transitions_mcp/__init__.py
video_transitions_mcp/main.py
mcpcn_video_transitions_mcp-0.1.5.dist-info/METADATA
mcpcn_video_transitions_mcp-0.1.5.dist-info/WHEEL
mcpcn_video_transitions_mcp-0.1.5.dist-info/entry_points.txt
mcpcn_video_transitions_mcp-0.1.5.dist-info/RECORD
