Metadata-Version: 2.4
Name: mcpcn-video-transitions-mcp
Version: 0.1.5
Summary: MCP server for adding multiple video entrance and exit animations (fade, slide, zoom, wipe, circle transitions)
Author-email: Your Name <your.email@example.com>
License: MIT
Keywords: animation,fade,ffmpeg,mcp,transitions,video
Classifier: Development Status :: 4 - Beta
Classifier: Intended Audience :: Developers
Classifier: License :: OSI Approved :: MIT License
Classifier: Programming Language :: Python :: 3
Classifier: Programming Language :: Python :: 3.12
Classifier: Topic :: Multimedia :: Video
Classifier: Topic :: Multimedia :: Video :: Non-Linear Editor
Classifier: Topic :: Software Development :: Libraries :: Python Modules
Requires-Python: >=3.12
Requires-Dist: ffmpeg-python>=0.2.0
Requires-Dist: mcp[cli]>=1.9.0
